valkyt/__init__.py
valkyt/server/__init__.py
valkyt/server/beanstalk/__init__.py
valkyt/server/beanstalk/connection.py
valkyt/server/beanstalk/functions.py
valkyt/server/kafka/__init__.py
valkyt/server/kafka/connection.py
valkyt/server/kafka/functions.py
valkyt/server/rabbyt/__init__.py
valkyt/server/rabbyt/connection.py
valkyt/server/rabbyt/functions.py
valkyt/server/redys/__init__.py
valkyt/server/redys/connection.py
valkyt/server/redys/functions.py
valkyt/server/s3/__init__.py
valkyt/server/s3/connection.py
valkyt/server/s3/functions.py
valkyt/server/ssdby/__init__.py
valkyt/server/ssdby/connection.py
valkyt/server/ssdby/functions.py
valkyt/unytest/Unytest.py
valkyt/unytest/__init__.py
valkyt/utils/__init__.py
valkyt/utils/casting.py
valkyt/utils/data_manipulation.py
valkyt/utils/datetimes.py
valkyt/utils/debugs.py
valkyt/utils/directory.py
valkyt/utils/downloader.py
valkyt/utils/endecode.py
valkyt/utils/fileIO.py
valkyt/utils/functions.py
valkyt/utils/html_parser.py
valkyt/utils/parser.py
valkyt/utils/stream.py
valkyt/utils/urlParsered.py
valkyt-0.2.3.dist-info/LICENSE
valkyt-0.2.3.dist-info/METADATA
valkyt-0.2.3.dist-info/WHEEL
valkyt-0.2.3.dist-info/top_level.txt
valkyt-0.2.3.dist-info/RECORD
