Metadata-Version: 2.1
Name: valkyt
Version: 0.2.3
Summary: Utils
Author: ryyos (Rio Dwi Saputra)
Author-email: <riodwi12174@gmail.com>
Keywords: valkyt,utils
Classifier: Development Status :: 1 - Planning
Classifier: Intended Audience :: Developers
Classifier: Programming Language :: Python
Classifier: Operating System :: Microsoft :: Windows
License-File: LICENSE
Requires-Dist: greenstalk
Requires-Dist: kafka-python
Requires-Dist: pika
Requires-Dist: loguru
Requires-Dist: redis
Requires-Dist: boto3
Requires-Dist: python-dateutil
Requires-Dist: dekimashita
Requires-Dist: requests
Requires-Dist: pyquery
Requires-Dist: bs4
Requires-Dist: click
Requires-Dist: s3fs
Requires-Dist: yt-dlp
Requires-Dist: fake-useragent
Requires-Dist: tqdm
